stacking_sats_pipeline/__init__.py
stacking_sats_pipeline/__main__.py
stacking_sats_pipeline/config.py
stacking_sats_pipeline/main.py
stacking_sats_pipeline/data/__init__.py
stacking_sats_pipeline/data/coinmetrics_loader.py
stacking_sats_pipeline/data/data_loader.py
stacking_sats_pipeline/data/fear_gread_loader.py
stacking_sats_pipeline/data/fred_loader.py
stacking_sats_pipeline-0.4.0.dist-info/licenses/LICENSE
stacking_sats_pipeline-0.4.0.dist-info/METADATA
stacking_sats_pipeline-0.4.0.dist-info/WHEEL
stacking_sats_pipeline-0.4.0.dist-info/entry_points.txt
stacking_sats_pipeline-0.4.0.dist-info/top_level.txt
stacking_sats_pipeline-0.4.0.dist-info/RECORD
