Metadata-Version: 2.4
Name: stacking-sats-pipeline
Version: 0.4.0
Summary: Hypertrial's Stacking Sats Library - Optimized Bitcoin DCA
Author-email: Matt Faltyn <matt@trilemmacapital.com>
Maintainer-email: Matt Faltyn <matt@trilemmacapital.com>
License: MIT License
Project-URL: Homepage, https://github.com/hypertrial/stacking_sats_pipeline
Project-URL: Repository, https://github.com/hypertrial/stacking_sats_pipeline
Project-URL: Documentation, https://github.com/hypertrial/stacking_sats_pipeline#readme
Project-URL: Bug Tracker, https://github.com/hypertrial/stacking_sats_pipeline/issues
Keywords: bitcoin,dca,backtesting,cryptocurrency,trading,strategy
Classifier: Development Status :: 4 - Beta
Classifier: Intended Audience :: Financial and Insurance Industry
Classifier: Intended Audience :: Developers
Classifier: Operating System :: OS Independent
Classifier: Programming Language :: Python :: 3
Classifier: Programming Language :: Python :: 3.11
Classifier: Programming Language :: Python :: 3.12
Classifier: Topic :: Office/Business :: Financial :: Investment
Classifier: Topic :: Scientific/Engineering :: Information Analysis
Requires-Python: >=3.11
License-File: LICENSE
Requires-Dist: pandas>=1.5.0
Requires-Dist: numpy>=1.21.0
Requires-Dist: requests>=2.28.0
Requires-Dist: matplotlib>=3.5.0
Requires-Dist: python-dotenv>=0.19.0
Requires-Dist: pyarrow>=10.0.0
Provides-Extra: dev
Requires-Dist: pytest>=7.0.0; extra == "dev"
Requires-Dist: ruff>=0.1.0; extra == "dev"
Requires-Dist: pre-commit>=3.0.0; extra == "dev"
Requires-Dist: autopep8>=2.0.0; extra == "dev"
Provides-Extra: tutorial
Requires-Dist: marimo>=0.1.0; extra == "tutorial"
Dynamic: license-file
